csv2xlsx.py
csv2xlsx-0.1.1.dist-info/WHEEL
csv2xlsx-0.1.1.dist-info/metadata.json
csv2xlsx-0.1.1.dist-info/METADATA
csv2xlsx-0.1.1.dist-info/RECORD
csv2xlsx-0.1.1.dist-info/DESCRIPTION.rst
csv2xlsx-0.1.1.dist-info/top_level.txt
csv2xlsx-0.1.1.dist-info/entry_points.txt
